pytest_helpers_namespace/__init__.py
pytest_helpers_namespace/plugin.py
pytest_helpers_namespace/version.py
pytest_helpers_namespace-2021.4.29.dist-info/AUTHORS.rst
pytest_helpers_namespace-2021.4.29.dist-info/AUTHORS.rst~
pytest_helpers_namespace-2021.4.29.dist-info/AUTHORS~
pytest_helpers_namespace-2021.4.29.dist-info/LICENSE
pytest_helpers_namespace-2021.4.29.dist-info/LICENSE~
pytest_helpers_namespace-2021.4.29.dist-info/METADATA
pytest_helpers_namespace-2021.4.29.dist-info/WHEEL
pytest_helpers_namespace-2021.4.29.dist-info/entry_points.txt
pytest_helpers_namespace-2021.4.29.dist-info/top_level.txt
pytest_helpers_namespace-2021.4.29.dist-info/RECORD
