Metadata-Version: 2.1
Name: pytest-helpers-namespace
Version: 2021.4.29
Summary: Pytest Helpers Namespace Plugin
Home-page: https://github.com/saltstack/pytest-helpers-namespace
Author: Pedro Algarvio
Author-email: pedro@algarvio.me
License: Apache Software License 2.0
Project-URL: Source, https://github.com/saltstack/pytest-helpers-namespace
Project-URL: Tracker, https://github.com/saltstack/pytest-helpers-namespace/issues
Project-URL: Documentation, https://pytest-helpers-namespace.readthedocs.io
Platform: unix
Platform: linux
Platform: osx
Platform: cygwin
Platform: win32
Classifier: Programming Language :: Python
Classifier: Programming Language :: Cython
Classifier: Programming Language :: Python :: 3
Classifier: Programming Language :: Python :: 3 :: Only
Classifier: Programming Language :: Python :: 3.5
Classifier: Programming Language :: Python :: 3.6
Classifier: Programming Language :: Python :: 3.7
Classifier: Programming Language :: Python :: 3.8
Classifier: Programming Language :: Python :: 3.9
Classifier: Development Status :: 5 - Production/Stable
Classifier: Intended Audience :: Developers
Classifier: License :: OSI Approved :: Apache Software License
Requires-Python: >=3.5
Requires-Dist: pytest (>=6.0.0)
Provides-Extra: docs
Requires-Dist: sphinx ; extra == 'docs'
Requires-Dist: sphinx-material-saltstack ; extra == 'docs'
Requires-Dist: sphinx-prompt ; extra == 'docs'
Requires-Dist: sphinxcontrib-spelling ; extra == 'docs'
Provides-Extra: lint
Requires-Dist: pylint (==2.4.4) ; extra == 'lint'
Requires-Dist: saltpylint (==2019.6.7) ; extra == 'lint'
Requires-Dist: pyenchant ; extra == 'lint'
Requires-Dist: black ; (python_version >= "3.7") and extra == 'lint'
Requires-Dist: reorder-python-imports ; (python_version >= "3.7") and extra == 'lint'
Provides-Extra: tests
